cmake_setup/__init__.py
cmake_setup/cmake/__init__.py
cmake_setup/headers/__init__.py
cmake_setup/utils/__init__.py
cmake_setup-0.1.1.dist-info/LICENSE
cmake_setup-0.1.1.dist-info/METADATA
cmake_setup-0.1.1.dist-info/WHEEL
cmake_setup-0.1.1.dist-info/top_level.txt
cmake_setup-0.1.1.dist-info/RECORD
