Metadata-Version: 2.1
Name: cmake-setup
Version: 0.1.1
Summary: Provides some usable cmake related build extensions
Home-page: https://github.com/galois-advertising/cmake_setup
Author: Ray Douglass
License: Apache 2.0
Platform: UNKNOWN
Classifier: Intended Audience :: Developers
Classifier: License :: OSI Approved :: Apache Software License
Classifier: Operating System :: POSIX :: Linux
Classifier: Programming Language :: Python :: 3
Classifier: Topic :: Software Development :: Build Tools
Requires-Dist: setuptools
